{
    "steps": [
        {
            "RH": 0,
            "RK": 0,
            "RF": 0,
            "C1": 0,
            "C2": 0.4,
            "CF": 0,
            "LH": 0,
            "LK": 0,
            "LF": 0
        },
        {
            "RH": -44,
            "RK": -3,
            "RF": 46,
            "C1": 0,
            "C2": 0.4,
            "CF": 1,
            "LH": -44,
            "LK": -3,
            "LF": 46
        },
        {
            "RH": -49,
            "RK": 73,
            "RF": -39,
            "C1": 65,
            "C2": 0.259,
            "CF": -88,
            "LH": -49,
            "LK": 73,
            "LF": -39
        },
        {
            "RH": -10,
            "RK": 73,
            "RF": -43,
            "C1": -51,
            "C2": 0.004,
            "CF": 33,
            "LH": -10,
            "LK": 73,
            "LF": -43
        },
        {
            "RH": 38,
            "RK": 9,
            "RF": -40,
            "C1": -7,
            "C2": 0.068,
            "CF": -21,
            "LH": 38,
            "LK": 9,
            "LF": -40
        },
        {
            "RH": -43,
            "RK": -5,
            "RF": 63,
            "C1": -5,
            "C2": 0.327,
            "CF": -3,
            "LH": -43,
            "LK": -5,
            "LF": 63
        },
        {
            "RH": -43,
            "RK": 87,
            "RF": -44,
            "C1": 46,
            "C2": 0.277,
            "CF": -83,
            "LH": -43,
            "LK": 87,
            "LF": -44
        },
        {
            "RH": -36,
            "RK": 70,
            "RF": -45,
            "C1": -54,
            "C2": 0.104,
            "CF": 28,
            "LH": -36,
            "LK": 70,
            "LF": -45
        },
        {
            "RH": 48,
            "RK": 2,
            "RF": -43,
            "C1": 0,
            "C2": 0.098,
            "CF": -30,
            "LH": 48,
            "LK": 2,
            "LF": -43
        },
        {
            "RH": 0,
            "RK": 0,
            "RF": 0,
            "C1": 0,
            "C2": 0.4,
            "CF": 0,
            "LH": 0,
            "LK": 0,
            "LF": 0
        }
    ]
}