{
    "steps": [
        {
            "RH": 0,
            "RK": 0,
            "RF": 0,
            "C1": 0,
            "C2": 0.4,
            "CF": 0,
            "LH": 0,
            "LK": 0,
            "LF": 0
        },
        {
            "RH": -46,
            "RK": 7,
            "RF": 47,
            "C1": -8,
            "C2": 0.4,
            "CF": -12,
            "LH": -46,
            "LK": 7,
            "LF": 47
        },
        {
            "RH": -54,
            "RK": 86,
            "RF": -55,
            "C1": 75,
            "C2": 0.393,
            "CF": -76,
            "LH": -54,
            "LK": 86,
            "LF": -55
        },
        {
            "RH": -22,
            "RK": 75,
            "RF": -46,
            "C1": -37,
            "C2": 0.025,
            "CF": 27,
            "LH": -22,
            "LK": 75,
            "LF": -46
        },
        {
            "RH": 36,
            "RK": -10,
            "RF": -40,
            "C1": -15,
            "C2": 0.0,
            "CF": -19,
            "LH": 36,
            "LK": -10,
            "LF": -40
        },
        {
            "RH": -48,
            "RK": -10,
            "RF": 52,
            "C1": -10,
            "C2": 0.4,
            "CF": 5,
            "LH": -48,
            "LK": -10,
            "LF": 52
        },
        {
            "RH": -31,
            "RK": 78,
            "RF": -39,
            "C1": 65,
            "C2": 0.249,
            "CF": -83,
            "LH": -31,
            "LK": 78,
            "LF": -39
        },
        {
            "RH": -19,
            "RK": 67,
            "RF": -52,
            "C1": -31,
            "C2": 0.028,
            "CF": 20,
            "LH": -19,
            "LK": 67,
            "LF": -52
        },
        {
            "RH": 45,
            "RK": 5,
            "RF": -45,
            "C1": -8,
            "C2": 0.094,
            "CF": -15,
            "LH": 45,
            "LK": 5,
            "LF": -45
        },
        {
            "RH": 0,
            "RK": 0,
            "RF": 0,
            "C1": 0,
            "C2": 0.4,
            "CF": 0,
            "LH": 0,
            "LK": 0,
            "LF": 0
        }
    ]
}