{
    "steps": [
        {
            "RH": 0,
            "RK": 0,
            "RF": 0,
            "C1": 0,
            "C2": 0.4,
            "CF": 0,
            "LH": 0,
            "LK": 0,
            "LF": 0
        },
        {
            "RH": -32,
            "RK": -7,
            "RF": 49,
            "C1": 11,
            "C2": 0.241,
            "CF": 16,
            "LH": -32,
            "LK": -7,
            "LF": 49
        },
        {
            "RH": -52,
            "RK": 70,
            "RF": -52,
            "C1": 61,
            "C2": 0.205,
            "CF": -83,
            "LH": -52,
            "LK": 70,
            "LF": -52
        },
        {
            "RH": -9,
            "RK": 68,
            "RF": -51,
            "C1": -50,
            "C2": 0.113,
            "CF": 25,
            "LH": -9,
            "LK": 68,
            "LF": -51
        },
        {
            "RH": 33,
            "RK": -2,
            "RF": -39,
            "C1": -27,
            "C2": 0.0,
            "CF": -22,
            "LH": 33,
            "LK": -2,
            "LF": -39
        },
        {
            "RH": -42,
            "RK": -13,
            "RF": 65,
            "C1": -5,
            "C2": 0.4,
            "CF": 9,
            "LH": -42,
            "LK": -13,
            "LF": 65
        },
        {
            "RH": -58,
            "RK": 93,
            "RF": -49,
            "C1": 54,
            "C2": 0.244,
            "CF": -84,
            "LH": -58,
            "LK": 93,
            "LF": -49
        },
        {
            "RH": -27,
            "RK": 65,
            "RF": -46,
            "C1": -53,
            "C2": 0.173,
            "CF": 40,
            "LH": -27,
            "LK": 65,
            "LF": -46
        },
        {
            "RH": 36,
            "RK": -5,
            "RF": -46,
            "C1": -16,
            "C2": 0.179,
            "CF": -24,
            "LH": 36,
            "LK": -5,
            "LF": -46
        },
        {
            "RH": 0,
            "RK": 0,
            "RF": 0,
            "C1": 0,
            "C2": 0.4,
            "CF": 0,
            "LH": 0,
            "LK": 0,
            "LF": 0
        }
    ]
}