{
    "steps": [
        {
            "RH": 0,
            "RK": 0,
            "RF": 0,
            "C1": 0,
            "C2": 0.4,
            "CF": 0,
            "LH": 0,
            "LK": 0,
            "LF": 0
        },
        {
            "RH": -47,
            "RK": 12,
            "RF": 43,
            "C1": 5,
            "C2": 0.35,
            "CF": -10,
            "LH": -47,
            "LK": 12,
            "LF": 43
        },
        {
            "RH": -57,
            "RK": 97,
            "RF": -43,
            "C1": 55,
            "C2": 0.4,
            "CF": -72,
            "LH": -57,
            "LK": 97,
            "LF": -43
        },
        {
            "RH": -22,
            "RK": 55,
            "RF": -48,
            "C1": -31,
            "C2": 0.136,
            "CF": 18,
            "LH": -22,
            "LK": 55,
            "LF": -48
        },
        {
            "RH": 48,
            "RK": 10,
            "RF": -46,
            "C1": -17,
            "C2": 0.0,
            "CF": -21,
            "LH": 48,
            "LK": 10,
            "LF": -46
        },
        {
            "RH": -30,
            "RK": 14,
            "RF": 43,
            "C1": -15,
            "C2": 0.259,
            "CF": -4,
            "LH": -30,
            "LK": 14,
            "LF": 43
        },
        {
            "RH": -48,
            "RK": 82,
            "RF": -52,
            "C1": 45,
            "C2": 0.4,
            "CF": -80,
            "LH": -48,
            "LK": 82,
            "LF": -52
        },
        {
            "RH": -23,
            "RK": 57,
            "RF": -43,
            "C1": -41,
            "C2": 0.0,
            "CF": 42,
            "LH": -23,
            "LK": 57,
            "LF": -43
        },
        {
            "RH": 50,
            "RK": 11,
            "RF": -29,
            "C1": -15,
            "C2": 0.0,
            "CF": -10,
            "LH": 50,
            "LK": 11,
            "LF": -29
        },
        {
            "RH": 0,
            "RK": 0,
            "RF": 0,
            "C1": 0,
            "C2": 0.4,
            "CF": 0,
            "LH": 0,
            "LK": 0,
            "LF": 0
        }
    ]
}