{
    "steps": [
        {
            "RH": 0,
            "RK": 0,
            "RF": 0,
            "C1": 0,
            "C2": 0.4,
            "CF": 0,
            "LH": 0,
            "LK": 0,
            "LF": 0
        },
        {
            "RH": -23,
            "RK": 2,
            "RF": 57,
            "C1": -5,
            "C2": 0.21,
            "CF": -9,
            "LH": -23,
            "LK": 2,
            "LF": 57
        },
        {
            "RH": -57,
            "RK": 97,
            "RF": -42,
            "C1": 50,
            "C2": 0.4,
            "CF": -79,
            "LH": -57,
            "LK": 97,
            "LF": -42
        },
        {
            "RH": -21,
            "RK": 75,
            "RF": -65,
            "C1": -36,
            "C2": 0.0,
            "CF": 31,
            "LH": -21,
            "LK": 75,
            "LF": -65
        },
        {
            "RH": 51,
            "RK": 4,
            "RF": -25,
            "C1": -6,
            "C2": 0.0,
            "CF": -6,
            "LH": 51,
            "LK": 4,
            "LF": -25
        },
        {
            "RH": -30,
            "RK": -13,
            "RF": 69,
            "C1": 1,
            "C2": 0.389,
            "CF": -8,
            "LH": -30,
            "LK": -13,
            "LF": 69
        },
        {
            "RH": -46,
            "RK": 88,
            "RF": -54,
            "C1": 58,
            "C2": 0.359,
            "CF": -80,
            "LH": -46,
            "LK": 88,
            "LF": -54
        },
        {
            "RH": -26,
            "RK": 65,
            "RF": -70,
            "C1": -50,
            "C2": 0.118,
            "CF": 32,
            "LH": -26,
            "LK": 65,
            "LF": -70
        },
        {
            "RH": 55,
            "RK": -6,
            "RF": -46,
            "C1": -4,
            "C2": 0.0,
            "CF": -18,
            "LH": 55,
            "LK": -6,
            "LF": -46
        },
        {
            "RH": 0,
            "RK": 0,
            "RF": 0,
            "C1": 0,
            "C2": 0.4,
            "CF": 0,
            "LH": 0,
            "LK": 0,
            "LF": 0
        }
    ]
}